frequsefuncs/__init__.py
frequsefuncs/setup.py
frequsefuncs/odps/__init__.py
frequsefuncs/odps/funcs.py
frequsefuncs/odps_passvar/__init__.py
frequsefuncs/odps_passvar/funcs.py
frequsefuncs/selfdev/__init__.py
frequsefuncs/selfdev/funcs.py
frequsefuncs/stat_test/__init__.py
frequsefuncs/stat_test/funcs.py
frequsefuncs-0.1.5.dist-info/METADATA
frequsefuncs-0.1.5.dist-info/WHEEL
frequsefuncs-0.1.5.dist-info/top_level.txt
frequsefuncs-0.1.5.dist-info/RECORD
