Metadata-Version: 2.1
Name: frequsefuncs
Version: 0.1.5
Summary: python package of frequently used functions
Author: y
Author-email: <y@outlook.com>
Keywords: python,first package
Classifier: Development Status :: 3 - Alpha
Classifier: Intended Audience :: Other Audience
Classifier: Programming Language :: Python :: 3
Classifier: Operating System :: MacOS :: MacOS X
